odoo/addons/product_contract_brand/README.rst
odoo/addons/product_contract_brand/__init__.py
odoo/addons/product_contract_brand/__manifest__.py
odoo/addons/product_contract_brand/i18n/product_contract_brand.pot
odoo/addons/product_contract_brand/models/__init__.py
odoo/addons/product_contract_brand/models/sale_order.py
odoo/addons/product_contract_brand/readme/CONTRIBUTORS.rst
odoo/addons/product_contract_brand/readme/DESCRIPTION.rst
odoo/addons/product_contract_brand/static/description/icon.png
odoo/addons/product_contract_brand/static/description/index.html
odoo/addons/product_contract_brand/tests/__init__.py
odoo/addons/product_contract_brand/tests/test_sale_order.py
odoo12_addon_product_contract_brand-12.0.1.0.0.99.dev4.dist-info/METADATA
odoo12_addon_product_contract_brand-12.0.1.0.0.99.dev4.dist-info/WHEEL
odoo12_addon_product_contract_brand-12.0.1.0.0.99.dev4.dist-info/top_level.txt
odoo12_addon_product_contract_brand-12.0.1.0.0.99.dev4.dist-info/RECORD
